simago/__init__.py
simago/__main__.py
simago/population.py
simago/probability.py
simago/yamlutils.py
simago-0.3.2.dist-info/LICENCE
simago-0.3.2.dist-info/METADATA
simago-0.3.2.dist-info/WHEEL
simago-0.3.2.dist-info/top_level.txt
simago-0.3.2.dist-info/RECORD
