Metadata-Version: 2.1
Name: simago
Version: 0.3.2
Summary: Randomly generate populations.
Home-page: https://github.com/alexanderharms/simago
Author: Alexander Harms
Author-email: a.g.j.harms@protonmail.com
Maintainer: Alexander Harms
Maintainer-email: a.g.j.harms@protonmail.com
License: GPL v3
Project-URL: Documentation, https://simago.readthedocs.io/en/latest
Project-URL: Source Code, https://github.com/alexanderharms/simago/
Keywords: simulation,open data
Platform: UNKNOWN
Classifier: Development Status :: 4 - Beta
Classifier: Natural Language :: English
Classifier: License :: OSI Approved :: GNU General Public License v3 (GPLv3)
Classifier: Operating System :: OS Independent
Classifier: Programming Language :: Python :: 3
Classifier: Programming Language :: Python :: 3.7
Classifier: Topic :: Scientific/Engineering
Requires-Dist: wheel
Requires-Dist: numpy
Requires-Dist: scipy
Requires-Dist: pandas
Requires-Dist: pyYAML
